adeptml/__init__.py
adeptml/configs.py
adeptml/ensemble.py
adeptml/models.py
adeptml/train_utils.py
adeptml-1.3.0.dist-info/LICENSE
adeptml-1.3.0.dist-info/METADATA
adeptml-1.3.0.dist-info/WHEEL
adeptml-1.3.0.dist-info/RECORD
