Metadata-Version: 2.1
Name: AdeptML
Version: 1.3.0
Summary: A High-Level PyTorch based Library for Hybrid Physics-Informed Machine Learning Models
Author: Manaswin Oddiraju
Requires-Python: >=3.9.0
Classifier: Programming Language :: Python :: 3
Classifier: Programming Language :: Python :: 3.9
Classifier: Programming Language :: Python :: 3.10
Classifier: Programming Language :: Python :: 3.11
Classifier: Programming Language :: Python :: 3.12
Classifier: Programming Language :: Python :: 3.13
Provides-Extra: docs
Requires-Dist: Sphinx (==7.3.7) ; extra == "docs"
Requires-Dist: joblib (>=1.3.2,<2.0.0)
Requires-Dist: sphinx-rtd-theme (==2.0.0) ; extra == "docs"
Requires-Dist: sphinxcontrib-napoleon (==0.7) ; extra == "docs"
Requires-Dist: tensorboard (>=2.16.2,<3.0.0)
Requires-Dist: torch (>=2.1.0,<3.0.0)
